Metadata-Version: 2.1
Name: MyPackage-007
Version: 0.0.1
Summary: Big
Author: Me
